LICENSE
MANIFEST.in
README.md
requirements.txt
setup.cfg
setup.py
PyDataWrap.egg-info/PKG-INFO
PyDataWrap.egg-info/SOURCES.txt
PyDataWrap.egg-info/dependency_links.txt
PyDataWrap.egg-info/not-zip-safe
PyDataWrap.egg-info/requires.txt
PyDataWrap.egg-info/top_level.txt
datawrap/__init__.py
datawrap/basewrap.py
datawrap/filedbwrap.py
datawrap/fileloader.py
datawrap/keydefaultdict.py
datawrap/listwrap.py
datawrap/rediswrap.py
datawrap/savable.py
datawrap/tableloader.py
datawrap/tablewrap.py
datawrap/external/__init__.py
datawrap/external/xmlparse.py