Metadata-Version: 1.1
Name: PyDataWrap
Version: 1.2.9
Summary: Tools for wrapping data and manipulating it in efficient ways
Home-page: https://github.com/OpenGov/python_data_wrap
Author: Matthew Seal
Author-email: mseal@opengov.com
License: LGPL 2.1
Download-URL: https://github.com/OpenGov/python_data_wrap/tarball/v1.2.9
Keywords: tables,data,databases,dictionary,filedb
Platform: UNKNOWN
Classifier: Development Status :: 4 - Beta
Classifier: Topic :: Utilities
Classifier: Topic :: Database :: Front-Ends
Classifier: License :: OSI Approved :: GNU Lesser General Public License v2 (LGPLv2)
Classifier: Natural Language :: English
Classifier: Programming Language :: Python :: 2.7
Classifier: Programming Language :: Python :: 3
